{
    "login": "NVnavkumar",
    "id": 97137715,
    "node_id": "U_kgDOBco0Mw",
    "avatar_url": "https://avatars.githubusercontent.com/u/97137715?v=4",
    "gravatar_id": "",
    "url": "https://api.github.com/users/NVnavkumar",
    "html_url": "https://github.com/NVnavkumar",
    "followers_url": "https://api.github.com/users/NVnavkumar/followers",
    "following_url": "https://api.github.com/users/NVnavkumar/following{/other_user}",
    "gists_url": "https://api.github.com/users/NVnavkumar/gists{/gist_id}",
    "starred_url": "https://api.github.com/users/NVnavkumar/starred{/owner}{/repo}",
    "subscriptions_url": "https://api.github.com/users/NVnavkumar/subscriptions",
    "organizations_url": "https://api.github.com/users/NVnavkumar/orgs",
    "repos_url": "https://api.github.com/users/NVnavkumar/repos",
    "events_url": "https://api.github.com/users/NVnavkumar/events{/privacy}",
    "received_events_url": "https://api.github.com/users/NVnavkumar/received_events",
    "type": "User",
    "site_admin": false,
    "name": "Navin Kumar",
    "company": "@NVIDIA",
    "blog": "",
    "location": null,
    "email": null,
    "hireable": null,
    "bio": "NVIDIA",
    "twitter_username": null,
    "public_repos": 9,
    "public_gists": 0,
    "followers": 2,
    "following": 0,
    "created_at": "2022-01-05T01:13:17Z",
    "updated_at": "2024-01-05T06:07:34Z"
}