{
    "url": "https://api.github.com/repos/NVIDIA/spark-rapids/issues/6184",
    "repository_url": "https://api.github.com/repos/NVIDIA/spark-rapids",
    "labels_url": "https://api.github.com/repos/NVIDIA/spark-rapids/issues/6184/labels{/name}",
    "comments_url": "https://api.github.com/repos/NVIDIA/spark-rapids/issues/6184/comments",
    "events_url": "https://api.github.com/repos/NVIDIA/spark-rapids/issues/6184/events",
    "html_url": "https://github.com/NVIDIA/spark-rapids/issues/6184",
    "id": 1324919581,
    "node_id": "I_kwDOD7z77c5O-Ksd",
    "number": 6184,
    "title": "[BUG] DayTimeIntervalType nested within StructType not a supported type",
    "user": {
        "login": "rwlee",
        "id": 10645552,
        "node_id": "MDQ6VXNlcjEwNjQ1NTUy",
        "avatar_url": "https://avatars.githubusercontent.com/u/10645552?v=4",
        "gravatar_id": "",
        "url": "https://api.github.com/users/rwlee",
        "html_url": "https://github.com/rwlee",
        "followers_url": "https://api.github.com/users/rwlee/followers",
        "following_url": "https://api.github.com/users/rwlee/following{/other_user}",
        "gists_url": "https://api.github.com/users/rwlee/gists{/gist_id}",
        "starred_url": "https://api.github.com/users/rwlee/starred{/owner}{/repo}",
        "subscriptions_url": "https://api.github.com/users/rwlee/subscriptions",
        "organizations_url": "https://api.github.com/users/rwlee/orgs",
        "repos_url": "https://api.github.com/users/rwlee/repos",
        "events_url": "https://api.github.com/users/rwlee/events{/privacy}",
        "received_events_url": "https://api.github.com/users/rwlee/received_events",
        "type": "User",
        "site_admin": false
    },
    "labels": [
        {
            "id": 2061735874,
            "node_id": "MDU6TGFiZWwyMDYxNzM1ODc0",
            "url": "https://api.github.com/repos/NVIDIA/spark-rapids/labels/bug",
            "name": "bug",
            "color": "d73a4a",
            "default": true,
            "description": "Something isn't working"
        }
    ],
    "state": "open",
    "locked": false,
    "assignee": null,
    "assignees": [],
    "milestone": null,
    "comments": 0,
    "created_at": "2022-08-01T20:13:24Z",
    "updated_at": "2022-08-02T20:50:06Z",
    "closed_at": null,
    "author_association": "COLLABORATOR",
    "active_lock_reason": null,
    "body": "Related to #6062 and #3149\r\n\r\n**Describe the bug**\r\nDayTimeIntervalType inside Structs are not a supported type. Found when adding new tests for struct binary ops in `cmp_test.py`. Adding intervals in structs via `StructGen([['child0', StructGen([['child2', DayTimeIntervalGen()]])], ['child1', short_gen]])` causes a test failure due to `part of the plan is not columnar`.\r\n\r\n```\r\n      !Expression <Literal> [[6084712057446794809],32767] cannot run on GPU because expression Literal [[6084712057446794809],32767] produces an unsupported type StructType(StructField(child0,StructType(StructField(child2,DayTimeIntervalType(0,3),true)),true),StructField(child1,ShortType,true))\r\n```\r\n\r\nReproduction:\r\nAdd `# @pytest.mark.parametrize('data_gen', [DayTimeIntervalGen(), StructGen([['child0', StructGen([['child2', DayTimeIntervalGen()]])], ['child1', short_gen]])], ids=idfn)` to any interval test and execute.\r\n\r\nResulting local output:\r\n```\r\n!Exec <ProjectExec> cannot run on GPU because not all expressions can be replaced\r\n  @Expression <Alias> (a#1812 >= [[6084712057446794809],32767]) AS (a >= struct(struct(CAST(INTERVAL '70424908 01:44:06.794809' DAY TO SECOND AS INTE\r\nRVAL DAY TO SECOND) AS child2) AS child0, CAST(32767 AS SMALLINT) AS child1))#1816 could run on GPU\r\n    @Expression <GreaterThanOrEqual> (a#1812 >= [[6084712057446794809],32767]) could run on GPU\r\n      @Expression <AttributeReference> a#1812 could run on GPU\r\n      !Expression <Literal> [[6084712057446794809],32767] cannot run on GPU because expression Literal [[6084712057446794809],32767] produces an unsupported type StructType(StructField(child0,StructType(StructField(child2,DayTimeIntervalType(0,3),true)),true),StructField(child1,ShortType,true))\r\n  @Expression <Alias> ([[-4024381387931422438],66] >= b#1813) AS (struct(struct(CAST(INTERVAL '-46578488 06:52:11.422438' DAY TO SECOND AS INTERVAL DAY TO SECOND) AS child2) AS child0, CAST(66 AS SMALLINT) AS child1) >= b)#1817 could run on GPU\r\n    @Expression <GreaterThanOrEqual> ([[-4024381387931422438],66] >= b#1813) could run on GPU\r\n      !Expression <Literal> [[-4024381387931422438],66] cannot run on GPU because expression Literal [[-4024381387931422438],66] produces an unsupported type StructType(StructField(child0,StructType(StructField(child2,DayTimeIntervalType(0,3),true)),true),StructField(child1,ShortType,true))\r\n      @Expression <AttributeReference> b#1813 could run on GPU\r\n  @Expression <Alias> null AS (NULL >= a)#1818 could run on GPU\r\n    @Expression <Literal> null could run on GPU\r\n  @Expression <Alias> null AS (b >= NULL)#1819 could run on GPU\r\n    @Expression <Literal> null could run on GPU\r\n  @Expression <Alias> (a#1812 >= b#1813) AS (a >= b)#1820 could run on GPU\r\n    @Expression <GreaterThanOrEqual> (a#1812 >= b#1813) could run on GPU\r\n      @Expression <AttributeReference> a#1812 could run on GPU\r\n      @Expression <AttributeReference> b#1813 could run on GPU\r\n  ! <RDDScanExec> cannot run on GPU because GPU does not currently support the operator class org.apache.spark.sql.execution.RDDScanExec\r\n    @Expression <AttributeReference> a#1812 could run on GPU\r\n    @Expression <AttributeReference> b#1813 could run on GPU\r\n\r\n22/08/01 19:42:19 ERROR GpuOverrideUtil: Encountered an exception applying GPU overrides java.lang.IllegalArgumentException: Part of the plan is not columnar class org.apache.spark.sql.execution.ProjectExec\r\nProject [(a#1812 >= [[6084712057446794809],32767]) AS (a >= struct(struct(CAST(INTERVAL '70424908 01:44:06.794809' DAY TO SECOND AS INTERVAL DAY TO SECOND) AS child2) AS child0, CAST(32767 AS SMALLINT) AS child1))#1816, ([[-4024381387931422438],66] >= b#1813) AS (struct(struct(CAST(INTERVAL '-46578488 06:52:11.422438' DAY TO SECOND AS INTERVAL DAY TO SECOND) AS child2) AS child0, CAST(66 AS SMALLINT) AS child1) >= b)#1817, null AS (NULL >= a)#1818, null AS (b >= NULL)#1819, (a#1812 >= b#1813) AS (a >= b)#1820]\r\n+- Scan ExistingRDD[a#1812,b#1813]\r\n\r\njava.lang.IllegalArgumentException: Part of the plan is not columnar class org.apache.spark.sql.execution.ProjectExec\r\nProject [(a#1812 >= [[6084712057446794809],32767]) AS (a >= struct(struct(CAST(INTERVAL '70424908 01:44:06.794809' DAY TO SECOND AS INTERVAL DAY TO SECOND) AS child2) AS child0, CAST(32767 AS SMALLINT) AS child1))#1816, ([[-4024381387931422438],66] >= b#1813) AS (struct(struct(CAST(INTERVAL '-46578488 06:52:11.422438' DAY TO SECOND AS INTERVAL DAY TO SECOND) AS child2) AS child0, CAST(66 AS SMALLINT) AS child1) >= b)#1817, null AS (NULL >= a)#1818, null AS (b >= NULL)#1819, (a#1812 >= b#1813) AS (a >= b)#1820]\r\n+- Scan ExistingRDD[a#1812,b#1813]\r\n```",
    "closed_by": null,
    "reactions": {
        "url": "https://api.github.com/repos/NVIDIA/spark-rapids/issues/6184/reactions",
        "total_count": 0,
        "+1": 0,
        "-1": 0,
        "laugh": 0,
        "hooray": 0,
        "confused": 0,
        "heart": 0,
        "rocket": 0,
        "eyes": 0
    },
    "timeline_url": "https://api.github.com/repos/NVIDIA/spark-rapids/issues/6184/timeline",
    "performed_via_github_app": null,
    "state_reason": null
}