{
    "url": "https://api.github.com/repos/NVIDIA/spark-rapids/issues/8843",
    "repository_url": "https://api.github.com/repos/NVIDIA/spark-rapids",
    "labels_url": "https://api.github.com/repos/NVIDIA/spark-rapids/issues/8843/labels{/name}",
    "comments_url": "https://api.github.com/repos/NVIDIA/spark-rapids/issues/8843/comments",
    "events_url": "https://api.github.com/repos/NVIDIA/spark-rapids/issues/8843/events",
    "html_url": "https://github.com/NVIDIA/spark-rapids/issues/8843",
    "id": 1825234249,
    "node_id": "I_kwDOD7z77c5syt1J",
    "number": 8843,
    "title": "[FEA] remove IMPROVED_TIMESTAMP_OPS",
    "user": {
        "login": "abellina",
        "id": 1901059,
        "node_id": "MDQ6VXNlcjE5MDEwNTk=",
        "avatar_url": "https://avatars.githubusercontent.com/u/1901059?v=4",
        "gravatar_id": "",
        "url": "https://api.github.com/users/abellina",
        "html_url": "https://github.com/abellina",
        "followers_url": "https://api.github.com/users/abellina/followers",
        "following_url": "https://api.github.com/users/abellina/following{/other_user}",
        "gists_url": "https://api.github.com/users/abellina/gists{/gist_id}",
        "starred_url": "https://api.github.com/users/abellina/starred{/owner}{/repo}",
        "subscriptions_url": "https://api.github.com/users/abellina/subscriptions",
        "organizations_url": "https://api.github.com/users/abellina/orgs",
        "repos_url": "https://api.github.com/users/abellina/repos",
        "events_url": "https://api.github.com/users/abellina/events{/privacy}",
        "received_events_url": "https://api.github.com/users/abellina/received_events",
        "type": "User",
        "site_admin": false
    },
    "labels": [
        {
            "id": 2061735884,
            "node_id": "MDU6TGFiZWwyMDYxNzM1ODg0",
            "url": "https://api.github.com/repos/NVIDIA/spark-rapids/labels/feature%20request",
            "name": "feature request",
            "color": "a2eeef",
            "default": false,
            "description": "New feature or request"
        },
        {
            "id": 2061735887,
            "node_id": "MDU6TGFiZWwyMDYxNzM1ODg3",
            "url": "https://api.github.com/repos/NVIDIA/spark-rapids/labels/good%20first%20issue",
            "name": "good first issue",
            "color": "7057ff",
            "default": true,
            "description": "Good for newcomers"
        },
        {
            "id": 3444490915,
            "node_id": "LA_kwDOD7z77c7NTsKj",
            "url": "https://api.github.com/repos/NVIDIA/spark-rapids/labels/tech%20debt",
            "name": "tech debt",
            "color": "0052cc",
            "default": false,
            "description": ""
        }
    ],
    "state": "open",
    "locked": false,
    "assignee": null,
    "assignees": [],
    "milestone": null,
    "comments": 0,
    "created_at": "2023-07-27T21:08:40Z",
    "updated_at": "2023-08-08T20:23:52Z",
    "closed_at": null,
    "author_association": "COLLABORATOR",
    "active_lock_reason": null,
    "body": "Currently, we have IMPROVED_TIMESTAMP_OPS that are disabled by default:\r\n\r\n```\r\n  val IMPROVED_TIMESTAMP_OPS =\r\n    conf(\"spark.rapids.sql.improvedTimeOps.enabled\")\r\n      .doc(\"When set to true, some operators will avoid overflowing by converting epoch days \" +\r\n          \"directly to seconds without first converting to microseconds\")\r\n      .booleanConf\r\n      .createWithDefault(false)\r\n```\r\n\r\nI am filing this issue to see if we can remove these (e.g. if we see reason to keep and make them the default then we should document what is left).\r\n\r\nThe Expressions that are off by default, and we could likely remove are:\r\n\r\n- `ToTimestampImproved`\r\n- `UnixTimestampImproved`\r\n- `ToUnixTimestampImproved`\r\n",
    "closed_by": null,
    "reactions": {
        "url": "https://api.github.com/repos/NVIDIA/spark-rapids/issues/8843/reactions",
        "total_count": 0,
        "+1": 0,
        "-1": 0,
        "laugh": 0,
        "hooray": 0,
        "confused": 0,
        "heart": 0,
        "rocket": 0,
        "eyes": 0
    },
    "timeline_url": "https://api.github.com/repos/NVIDIA/spark-rapids/issues/8843/timeline",
    "performed_via_github_app": null,
    "state_reason": null
}