{
    "url": "https://api.github.com/repos/rapidsai/cudf/issues/12610",
    "repository_url": "https://api.github.com/repos/rapidsai/cudf",
    "labels_url": "https://api.github.com/repos/rapidsai/cudf/issues/12610/labels{/name}",
    "comments_url": "https://api.github.com/repos/rapidsai/cudf/issues/12610/comments",
    "events_url": "https://api.github.com/repos/rapidsai/cudf/issues/12610/events",
    "html_url": "https://github.com/rapidsai/cudf/issues/12610",
    "id": 1557172978,
    "node_id": "I_kwDOBWUGps5c0JLy",
    "number": 12610,
    "title": "[FEA] Java Table concatenate should gracefully handle the single table degenerate case",
    "user": {
        "login": "jlowe",
        "id": 1360766,
        "node_id": "MDQ6VXNlcjEzNjA3NjY=",
        "avatar_url": "https://avatars.githubusercontent.com/u/1360766?v=4",
        "gravatar_id": "",
        "url": "https://api.github.com/users/jlowe",
        "html_url": "https://github.com/jlowe",
        "followers_url": "https://api.github.com/users/jlowe/followers",
        "following_url": "https://api.github.com/users/jlowe/following{/other_user}",
        "gists_url": "https://api.github.com/users/jlowe/gists{/gist_id}",
        "starred_url": "https://api.github.com/users/jlowe/starred{/owner}{/repo}",
        "subscriptions_url": "https://api.github.com/users/jlowe/subscriptions",
        "organizations_url": "https://api.github.com/users/jlowe/orgs",
        "repos_url": "https://api.github.com/users/jlowe/repos",
        "events_url": "https://api.github.com/users/jlowe/events{/privacy}",
        "received_events_url": "https://api.github.com/users/jlowe/received_events",
        "type": "User",
        "site_admin": false
    },
    "labels": [
        {
            "id": 599626561,
            "node_id": "MDU6TGFiZWw1OTk2MjY1NjE=",
            "url": "https://api.github.com/repos/rapidsai/cudf/labels/feature%20request",
            "name": "feature request",
            "color": "a2eeef",
            "default": false,
            "description": "New feature or request"
        },
        {
            "id": 1013987352,
            "node_id": "MDU6TGFiZWwxMDEzOTg3MzUy",
            "url": "https://api.github.com/repos/rapidsai/cudf/labels/0%20-%20Backlog",
            "name": "0 - Backlog",
            "color": "d4c5f9",
            "default": false,
            "description": "In queue waiting for assignment"
        },
        {
            "id": 1405145623,
            "node_id": "MDU6TGFiZWwxNDA1MTQ1NjIz",
            "url": "https://api.github.com/repos/rapidsai/cudf/labels/Java",
            "name": "Java",
            "color": "006b75",
            "default": false,
            "description": "Affects Java cuDF API."
        }
    ],
    "state": "open",
    "locked": false,
    "assignee": null,
    "assignees": [],
    "milestone": null,
    "comments": 0,
    "created_at": "2023-01-25T19:38:19Z",
    "updated_at": "2023-06-06T04:16:11Z",
    "closed_at": null,
    "author_association": "MEMBER",
    "active_lock_reason": null,
    "body": "**Is your feature request related to a problem? Please describe.**\r\nWhen calling Table.concatenate with a single table, it throws an IllegalArgumentException rather than simply returning a new table with the same columns as the single input table.  This forces calling code to special-case this scenario to avoid a crash.\r\n\r\n**Describe the solution you'd like**\r\nTable.concatenate should handle a degenerate concatenate of a single table by returning a new table containing the same columns as the original input table (i.e.: zero-copy via refcount)\r\n\r\n**Describe alternatives you've considered**\r\nLeave it as-is, callers must each special-case this scenario to avoid a crash.",
    "closed_by": null,
    "reactions": {
        "url": "https://api.github.com/repos/rapidsai/cudf/issues/12610/reactions",
        "total_count": 0,
        "+1": 0,
        "-1": 0,
        "laugh": 0,
        "hooray": 0,
        "confused": 0,
        "heart": 0,
        "rocket": 0,
        "eyes": 0
    },
    "timeline_url": "https://api.github.com/repos/rapidsai/cudf/issues/12610/timeline",
    "performed_via_github_app": null,
    "state_reason": null
}