{
    "url": "https://api.github.com/repos/rapidsai/cudf/issues/2135",
    "repository_url": "https://api.github.com/repos/rapidsai/cudf",
    "labels_url": "https://api.github.com/repos/rapidsai/cudf/issues/2135/labels{/name}",
    "comments_url": "https://api.github.com/repos/rapidsai/cudf/issues/2135/comments",
    "events_url": "https://api.github.com/repos/rapidsai/cudf/issues/2135/events",
    "html_url": "https://github.com/rapidsai/cudf/issues/2135",
    "id": 461656798,
    "node_id": "MDU6SXNzdWU0NjE2NTY3OTg=",
    "number": 2135,
    "title": "[FEA] Add more functionality to rolling objects",
    "user": {
        "login": "chinmaychandak",
        "id": 47901991,
        "node_id": "MDQ6VXNlcjQ3OTAxOTkx",
        "avatar_url": "https://avatars.githubusercontent.com/u/47901991?v=4",
        "gravatar_id": "",
        "url": "https://api.github.com/users/chinmaychandak",
        "html_url": "https://github.com/chinmaychandak",
        "followers_url": "https://api.github.com/users/chinmaychandak/followers",
        "following_url": "https://api.github.com/users/chinmaychandak/following{/other_user}",
        "gists_url": "https://api.github.com/users/chinmaychandak/gists{/gist_id}",
        "starred_url": "https://api.github.com/users/chinmaychandak/starred{/owner}{/repo}",
        "subscriptions_url": "https://api.github.com/users/chinmaychandak/subscriptions",
        "organizations_url": "https://api.github.com/users/chinmaychandak/orgs",
        "repos_url": "https://api.github.com/users/chinmaychandak/repos",
        "events_url": "https://api.github.com/users/chinmaychandak/events{/privacy}",
        "received_events_url": "https://api.github.com/users/chinmaychandak/received_events",
        "type": "User",
        "site_admin": false
    },
    "labels": [
        {
            "id": 599626561,
            "node_id": "MDU6TGFiZWw1OTk2MjY1NjE=",
            "url": "https://api.github.com/repos/rapidsai/cudf/labels/feature%20request",
            "name": "feature request",
            "color": "a2eeef",
            "default": false,
            "description": "New feature or request"
        },
        {
            "id": 1139740666,
            "node_id": "MDU6TGFiZWwxMTM5NzQwNjY2",
            "url": "https://api.github.com/repos/rapidsai/cudf/labels/libcudf",
            "name": "libcudf",
            "color": "c5def5",
            "default": false,
            "description": "Affects libcudf (C++/CUDA) code."
        },
        {
            "id": 1139741213,
            "node_id": "MDU6TGFiZWwxMTM5NzQxMjEz",
            "url": "https://api.github.com/repos/rapidsai/cudf/labels/Python",
            "name": "Python",
            "color": "1d76db",
            "default": false,
            "description": "Affects Python cuDF API."
        }
    ],
    "state": "open",
    "locked": false,
    "assignee": null,
    "assignees": [],
    "milestone": {
        "url": "https://api.github.com/repos/rapidsai/cudf/milestones/5",
        "html_url": "https://github.com/rapidsai/cudf/milestone/5",
        "labels_url": "https://api.github.com/repos/rapidsai/cudf/milestones/5/labels",
        "id": 6955120,
        "node_id": "MI_kwDOBWUGps4AaiBw",
        "number": 5,
        "title": "Pandas API Alignment and Coverage",
        "description": "",
        "creator": {
            "login": "beckernick",
            "id": 8457388,
            "node_id": "MDQ6VXNlcjg0NTczODg=",
            "avatar_url": "https://avatars.githubusercontent.com/u/8457388?v=4",
            "gravatar_id": "",
            "url": "https://api.github.com/users/beckernick",
            "html_url": "https://github.com/beckernick",
            "followers_url": "https://api.github.com/users/beckernick/followers",
            "following_url": "https://api.github.com/users/beckernick/following{/other_user}",
            "gists_url": "https://api.github.com/users/beckernick/gists{/gist_id}",
            "starred_url": "https://api.github.com/users/beckernick/starred{/owner}{/repo}",
            "subscriptions_url": "https://api.github.com/users/beckernick/subscriptions",
            "organizations_url": "https://api.github.com/users/beckernick/orgs",
            "repos_url": "https://api.github.com/users/beckernick/repos",
            "events_url": "https://api.github.com/users/beckernick/events{/privacy}",
            "received_events_url": "https://api.github.com/users/beckernick/received_events",
            "type": "User",
            "site_admin": false
        },
        "open_issues": 114,
        "closed_issues": 124,
        "state": "open",
        "created_at": "2021-07-16T17:49:59Z",
        "updated_at": "2024-06-03T17:45:11Z",
        "due_on": null,
        "closed_at": null
    },
    "comments": 5,
    "created_at": "2019-06-27T17:30:18Z",
    "updated_at": "2024-05-10T22:21:10Z",
    "closed_at": null,
    "author_association": "CONTRIBUTOR",
    "active_lock_reason": null,
    "body": "For our use cases, it would be helpful if rolling window objects have more functionality.\r\n\r\nBasically, this would mean adding support for median, variance, standard deviation, quantile, and aggregate functions for rolling objects.\r\n\r\nAn example of support for aggregate() is below:\r\n```\r\nimport cudf\r\ndf = cudf.DataFrame({'x': np.arange(10)})\r\nprint(df.x.rolling(2).aggregate({'x':'max'}))\r\n```\r\n\r\n**EDIT**\r\nAs of 7/11/2022, the following methods exist: min, mean, max, std, var, sum, count, apply. What remains is to implement:\r\n- [ ] median (see also #6276)\r\n- [ ] quantile\r\n- [ ] aggregate",
    "closed_by": null,
    "reactions": {
        "url": "https://api.github.com/repos/rapidsai/cudf/issues/2135/reactions",
        "total_count": 0,
        "+1": 0,
        "-1": 0,
        "laugh": 0,
        "hooray": 0,
        "confused": 0,
        "heart": 0,
        "rocket": 0,
        "eyes": 0
    },
    "timeline_url": "https://api.github.com/repos/rapidsai/cudf/issues/2135/timeline",
    "performed_via_github_app": null,
    "state_reason": null
}