{
    "url": "https://api.github.com/repos/rapidsai/cudf/issues/1480",
    "repository_url": "https://api.github.com/repos/rapidsai/cudf",
    "labels_url": "https://api.github.com/repos/rapidsai/cudf/issues/1480/labels{/name}",
    "comments_url": "https://api.github.com/repos/rapidsai/cudf/issues/1480/comments",
    "events_url": "https://api.github.com/repos/rapidsai/cudf/issues/1480/events",
    "html_url": "https://github.com/rapidsai/cudf/issues/1480",
    "id": 435836695,
    "node_id": "MDU6SXNzdWU0MzU4MzY2OTU=",
    "number": 1480,
    "title": "[FEA] Implement find_valid_index and its permutations (first_ and last_)",
    "user": {
        "login": "beckernick",
        "id": 8457388,
        "node_id": "MDQ6VXNlcjg0NTczODg=",
        "avatar_url": "https://avatars.githubusercontent.com/u/8457388?v=4",
        "gravatar_id": "",
        "url": "https://api.github.com/users/beckernick",
        "html_url": "https://github.com/beckernick",
        "followers_url": "https://api.github.com/users/beckernick/followers",
        "following_url": "https://api.github.com/users/beckernick/following{/other_user}",
        "gists_url": "https://api.github.com/users/beckernick/gists{/gist_id}",
        "starred_url": "https://api.github.com/users/beckernick/starred{/owner}{/repo}",
        "subscriptions_url": "https://api.github.com/users/beckernick/subscriptions",
        "organizations_url": "https://api.github.com/users/beckernick/orgs",
        "repos_url": "https://api.github.com/users/beckernick/repos",
        "events_url": "https://api.github.com/users/beckernick/events{/privacy}",
        "received_events_url": "https://api.github.com/users/beckernick/received_events",
        "type": "User",
        "site_admin": false
    },
    "labels": [
        {
            "id": 599626561,
            "node_id": "MDU6TGFiZWw1OTk2MjY1NjE=",
            "url": "https://api.github.com/repos/rapidsai/cudf/labels/feature%20request",
            "name": "feature request",
            "color": "a2eeef",
            "default": false,
            "description": "New feature or request"
        },
        {
            "id": 1016332948,
            "node_id": "MDU6TGFiZWwxMDE2MzMyOTQ4",
            "url": "https://api.github.com/repos/rapidsai/cudf/labels/good%20first%20issue",
            "name": "good first issue",
            "color": "7057ff",
            "default": true,
            "description": "Good for newcomers"
        },
        {
            "id": 1139741213,
            "node_id": "MDU6TGFiZWwxMTM5NzQxMjEz",
            "url": "https://api.github.com/repos/rapidsai/cudf/labels/Python",
            "name": "Python",
            "color": "1d76db",
            "default": false,
            "description": "Affects Python cuDF API."
        }
    ],
    "state": "open",
    "locked": false,
    "assignee": null,
    "assignees": [],
    "milestone": {
        "url": "https://api.github.com/repos/rapidsai/cudf/milestones/5",
        "html_url": "https://github.com/rapidsai/cudf/milestone/5",
        "labels_url": "https://api.github.com/repos/rapidsai/cudf/milestones/5/labels",
        "id": 6955120,
        "node_id": "MI_kwDOBWUGps4AaiBw",
        "number": 5,
        "title": "Pandas API Alignment and Coverage",
        "description": "",
        "creator": {
            "login": "beckernick",
            "id": 8457388,
            "node_id": "MDQ6VXNlcjg0NTczODg=",
            "avatar_url": "https://avatars.githubusercontent.com/u/8457388?v=4",
            "gravatar_id": "",
            "url": "https://api.github.com/users/beckernick",
            "html_url": "https://github.com/beckernick",
            "followers_url": "https://api.github.com/users/beckernick/followers",
            "following_url": "https://api.github.com/users/beckernick/following{/other_user}",
            "gists_url": "https://api.github.com/users/beckernick/gists{/gist_id}",
            "starred_url": "https://api.github.com/users/beckernick/starred{/owner}{/repo}",
            "subscriptions_url": "https://api.github.com/users/beckernick/subscriptions",
            "organizations_url": "https://api.github.com/users/beckernick/orgs",
            "repos_url": "https://api.github.com/users/beckernick/repos",
            "events_url": "https://api.github.com/users/beckernick/events{/privacy}",
            "received_events_url": "https://api.github.com/users/beckernick/received_events",
            "type": "User",
            "site_admin": false
        },
        "open_issues": 114,
        "closed_issues": 124,
        "state": "open",
        "created_at": "2021-07-16T17:49:59Z",
        "updated_at": "2024-06-03T17:45:11Z",
        "due_on": null,
        "closed_at": null
    },
    "comments": 4,
    "created_at": "2019-04-22T18:36:54Z",
    "updated_at": "2024-05-10T23:47:10Z",
    "closed_at": null,
    "author_association": "MEMBER",
    "active_lock_reason": null,
    "body": "**Is your feature request related to a problem? Please describe.**\r\nAs a user, I'd like to be able to call `last_valid_index` or `first_valid_index` to get the index of the first/last non-null value in a Series.\r\n\r\n**Describe the solution you'd like**\r\nI'd like to be able to do the following with cudf:\r\n```\r\nimport pandas as pd\r\nimport numpy as np\r\n\r\nser1 = [1,2,3,4]\r\nser2 = [1,2,3,None]\r\npdf = pd.DataFrame({'a':ser1, 'b':ser2})\r\nprint(pdf.b.last_valid_index())\r\n2\r\n```\r\n\r\n**Additional context**\r\nThe pandas implementation is [here](https://github.com/pandas-dev/pandas/blob/v0.24.2/pandas/core/generic.py#L10195). This will help with API compatibility.\r\n",
    "closed_by": null,
    "reactions": {
        "url": "https://api.github.com/repos/rapidsai/cudf/issues/1480/reactions",
        "total_count": 0,
        "+1": 0,
        "-1": 0,
        "laugh": 0,
        "hooray": 0,
        "confused": 0,
        "heart": 0,
        "rocket": 0,
        "eyes": 0
    },
    "timeline_url": "https://api.github.com/repos/rapidsai/cudf/issues/1480/timeline",
    "performed_via_github_app": null,
    "state_reason": null
}