{
    "url": "https://api.github.com/repos/rapidsai/cudf/issues/10183",
    "repository_url": "https://api.github.com/repos/rapidsai/cudf",
    "labels_url": "https://api.github.com/repos/rapidsai/cudf/issues/10183/labels{/name}",
    "comments_url": "https://api.github.com/repos/rapidsai/cudf/issues/10183/comments",
    "events_url": "https://api.github.com/repos/rapidsai/cudf/issues/10183/events",
    "html_url": "https://github.com/rapidsai/cudf/issues/10183",
    "id": 1120962727,
    "node_id": "I_kwDOBWUGps5C0Iin",
    "number": 10183,
    "title": "[FEA] Unify distinct_count column/table APIs.",
    "user": {
        "login": "bdice",
        "id": 3943761,
        "node_id": "MDQ6VXNlcjM5NDM3NjE=",
        "avatar_url": "https://avatars.githubusercontent.com/u/3943761?v=4",
        "gravatar_id": "",
        "url": "https://api.github.com/users/bdice",
        "html_url": "https://github.com/bdice",
        "followers_url": "https://api.github.com/users/bdice/followers",
        "following_url": "https://api.github.com/users/bdice/following{/other_user}",
        "gists_url": "https://api.github.com/users/bdice/gists{/gist_id}",
        "starred_url": "https://api.github.com/users/bdice/starred{/owner}{/repo}",
        "subscriptions_url": "https://api.github.com/users/bdice/subscriptions",
        "organizations_url": "https://api.github.com/users/bdice/orgs",
        "repos_url": "https://api.github.com/users/bdice/repos",
        "events_url": "https://api.github.com/users/bdice/events{/privacy}",
        "received_events_url": "https://api.github.com/users/bdice/received_events",
        "type": "User",
        "site_admin": false
    },
    "labels": [
        {
            "id": 599626561,
            "node_id": "MDU6TGFiZWw1OTk2MjY1NjE=",
            "url": "https://api.github.com/repos/rapidsai/cudf/labels/feature%20request",
            "name": "feature request",
            "color": "a2eeef",
            "default": false,
            "description": "New feature or request"
        },
        {
            "id": 1013987352,
            "node_id": "MDU6TGFiZWwxMDEzOTg3MzUy",
            "url": "https://api.github.com/repos/rapidsai/cudf/labels/0%20-%20Backlog",
            "name": "0 - Backlog",
            "color": "d4c5f9",
            "default": false,
            "description": "In queue waiting for assignment"
        },
        {
            "id": 1139740666,
            "node_id": "MDU6TGFiZWwxMTM5NzQwNjY2",
            "url": "https://api.github.com/repos/rapidsai/cudf/labels/libcudf",
            "name": "libcudf",
            "color": "c5def5",
            "default": false,
            "description": "Affects libcudf (C++/CUDA) code."
        }
    ],
    "state": "open",
    "locked": false,
    "assignee": {
        "login": "PointKernel",
        "id": 12716979,
        "node_id": "MDQ6VXNlcjEyNzE2OTc5",
        "avatar_url": "https://avatars.githubusercontent.com/u/12716979?v=4",
        "gravatar_id": "",
        "url": "https://api.github.com/users/PointKernel",
        "html_url": "https://github.com/PointKernel",
        "followers_url": "https://api.github.com/users/PointKernel/followers",
        "following_url": "https://api.github.com/users/PointKernel/following{/other_user}",
        "gists_url": "https://api.github.com/users/PointKernel/gists{/gist_id}",
        "starred_url": "https://api.github.com/users/PointKernel/starred{/owner}{/repo}",
        "subscriptions_url": "https://api.github.com/users/PointKernel/subscriptions",
        "organizations_url": "https://api.github.com/users/PointKernel/orgs",
        "repos_url": "https://api.github.com/users/PointKernel/repos",
        "events_url": "https://api.github.com/users/PointKernel/events{/privacy}",
        "received_events_url": "https://api.github.com/users/PointKernel/received_events",
        "type": "User",
        "site_admin": false
    },
    "assignees": [
        {
            "login": "PointKernel",
            "id": 12716979,
            "node_id": "MDQ6VXNlcjEyNzE2OTc5",
            "avatar_url": "https://avatars.githubusercontent.com/u/12716979?v=4",
            "gravatar_id": "",
            "url": "https://api.github.com/users/PointKernel",
            "html_url": "https://github.com/PointKernel",
            "followers_url": "https://api.github.com/users/PointKernel/followers",
            "following_url": "https://api.github.com/users/PointKernel/following{/other_user}",
            "gists_url": "https://api.github.com/users/PointKernel/gists{/gist_id}",
            "starred_url": "https://api.github.com/users/PointKernel/starred{/owner}{/repo}",
            "subscriptions_url": "https://api.github.com/users/PointKernel/subscriptions",
            "organizations_url": "https://api.github.com/users/PointKernel/orgs",
            "repos_url": "https://api.github.com/users/PointKernel/repos",
            "events_url": "https://api.github.com/users/PointKernel/events{/privacy}",
            "received_events_url": "https://api.github.com/users/PointKernel/received_events",
            "type": "User",
            "site_admin": false
        },
        {
            "login": "divyegala",
            "id": 14876585,
            "node_id": "MDQ6VXNlcjE0ODc2NTg1",
            "avatar_url": "https://avatars.githubusercontent.com/u/14876585?v=4",
            "gravatar_id": "",
            "url": "https://api.github.com/users/divyegala",
            "html_url": "https://github.com/divyegala",
            "followers_url": "https://api.github.com/users/divyegala/followers",
            "following_url": "https://api.github.com/users/divyegala/following{/other_user}",
            "gists_url": "https://api.github.com/users/divyegala/gists{/gist_id}",
            "starred_url": "https://api.github.com/users/divyegala/starred{/owner}{/repo}",
            "subscriptions_url": "https://api.github.com/users/divyegala/subscriptions",
            "organizations_url": "https://api.github.com/users/divyegala/orgs",
            "repos_url": "https://api.github.com/users/divyegala/repos",
            "events_url": "https://api.github.com/users/divyegala/events{/privacy}",
            "received_events_url": "https://api.github.com/users/divyegala/received_events",
            "type": "User",
            "site_admin": false
        }
    ],
    "milestone": {
        "url": "https://api.github.com/repos/rapidsai/cudf/milestones/25",
        "html_url": "https://github.com/rapidsai/cudf/milestone/25",
        "labels_url": "https://api.github.com/repos/rapidsai/cudf/milestones/25/labels",
        "id": 8693498,
        "node_id": "MI_kwDOBWUGps4AhKb6",
        "number": 25,
        "title": "Helps libcudf C++ integrations",
        "description": "",
        "creator": {
            "login": "GregoryKimball",
            "id": 12725111,
            "node_id": "MDQ6VXNlcjEyNzI1MTEx",
            "avatar_url": "https://avatars.githubusercontent.com/u/12725111?v=4",
            "gravatar_id": "",
            "url": "https://api.github.com/users/GregoryKimball",
            "html_url": "https://github.com/GregoryKimball",
            "followers_url": "https://api.github.com/users/GregoryKimball/followers",
            "following_url": "https://api.github.com/users/GregoryKimball/following{/other_user}",
            "gists_url": "https://api.github.com/users/GregoryKimball/gists{/gist_id}",
            "starred_url": "https://api.github.com/users/GregoryKimball/starred{/owner}{/repo}",
            "subscriptions_url": "https://api.github.com/users/GregoryKimball/subscriptions",
            "organizations_url": "https://api.github.com/users/GregoryKimball/orgs",
            "repos_url": "https://api.github.com/users/GregoryKimball/repos",
            "events_url": "https://api.github.com/users/GregoryKimball/events{/privacy}",
            "received_events_url": "https://api.github.com/users/GregoryKimball/received_events",
            "type": "User",
            "site_admin": false
        },
        "open_issues": 14,
        "closed_issues": 7,
        "state": "open",
        "created_at": "2022-11-26T17:28:14Z",
        "updated_at": "2024-05-13T23:56:47Z",
        "due_on": null,
        "closed_at": null
    },
    "comments": 4,
    "created_at": "2022-02-01T17:00:15Z",
    "updated_at": "2023-01-04T00:08:21Z",
    "closed_at": null,
    "author_association": "CONTRIBUTOR",
    "active_lock_reason": null,
    "body": "**Is your feature request related to a problem? Please describe.**\r\nWhile reviewing #10030, I found that the column and table algorithms for `distinct_count` have completely different flags for null and NaN handling. The column API has `null_policy` (include/exclude) and `nan_policy` (NaN is/isn't null), while the table API has `null_equality` (nulls are equal/unequal).\r\n\r\nThis also applies to `unordered_distinct_count`, introduced in #10030.\r\n\r\n**Describe the solution you'd like**\r\nThe distinct count APIs for column/table should use the same flags (meaning that all three flags should probably be available to both APIs). This would also allow the column API to be a pass-through implementation of the table API, with a table composed of only that column, rather than having two implementations ([table](https://github.com/rapidsai/cudf/blob/2c6b0dac61a6671642bb5b076e910e20e2bdd1b6/cpp/src/stream_compaction/distinct_count.cu#L38-L62), [column](https://github.com/rapidsai/cudf/blob/2c6b0dac61a6671642bb5b076e910e20e2bdd1b6/cpp/src/stream_compaction/distinct_count.cu#L140-L168)).",
    "closed_by": null,
    "reactions": {
        "url": "https://api.github.com/repos/rapidsai/cudf/issues/10183/reactions",
        "total_count": 0,
        "+1": 0,
        "-1": 0,
        "laugh": 0,
        "hooray": 0,
        "confused": 0,
        "heart": 0,
        "rocket": 0,
        "eyes": 0
    },
    "timeline_url": "https://api.github.com/repos/rapidsai/cudf/issues/10183/timeline",
    "performed_via_github_app": null,
    "state_reason": null
}