{
    "url": "https://api.github.com/repos/rapidsai/cudf/issues/14794",
    "repository_url": "https://api.github.com/repos/rapidsai/cudf",
    "labels_url": "https://api.github.com/repos/rapidsai/cudf/issues/14794/labels{/name}",
    "comments_url": "https://api.github.com/repos/rapidsai/cudf/issues/14794/comments",
    "events_url": "https://api.github.com/repos/rapidsai/cudf/issues/14794/events",
    "html_url": "https://github.com/rapidsai/cudf/issues/14794",
    "id": 2090331962,
    "node_id": "I_kwDOBWUGps58l-86",
    "number": 14794,
    "title": "[BUG] sort_values fails on groupby aggregation",
    "user": {
        "login": "jacobtomlinson",
        "id": 1610850,
        "node_id": "MDQ6VXNlcjE2MTA4NTA=",
        "avatar_url": "https://avatars.githubusercontent.com/u/1610850?v=4",
        "gravatar_id": "",
        "url": "https://api.github.com/users/jacobtomlinson",
        "html_url": "https://github.com/jacobtomlinson",
        "followers_url": "https://api.github.com/users/jacobtomlinson/followers",
        "following_url": "https://api.github.com/users/jacobtomlinson/following{/other_user}",
        "gists_url": "https://api.github.com/users/jacobtomlinson/gists{/gist_id}",
        "starred_url": "https://api.github.com/users/jacobtomlinson/starred{/owner}{/repo}",
        "subscriptions_url": "https://api.github.com/users/jacobtomlinson/subscriptions",
        "organizations_url": "https://api.github.com/users/jacobtomlinson/orgs",
        "repos_url": "https://api.github.com/users/jacobtomlinson/repos",
        "events_url": "https://api.github.com/users/jacobtomlinson/events{/privacy}",
        "received_events_url": "https://api.github.com/users/jacobtomlinson/received_events",
        "type": "User",
        "site_admin": false
    },
    "labels": [
        {
            "id": 599626559,
            "node_id": "MDU6TGFiZWw1OTk2MjY1NTk=",
            "url": "https://api.github.com/repos/rapidsai/cudf/labels/bug",
            "name": "bug",
            "color": "d73a4a",
            "default": true,
            "description": "Something isn't working"
        }
    ],
    "state": "open",
    "locked": false,
    "assignee": null,
    "assignees": [],
    "milestone": null,
    "comments": 0,
    "created_at": "2024-01-19T11:27:04Z",
    "updated_at": "2024-03-04T15:41:57Z",
    "closed_at": null,
    "author_association": "MEMBER",
    "active_lock_reason": null,
    "body": "**Describe the bug**\r\nThis bug was found while playing around with the [One Billion Row Challenge](https://medium.com/coiled-hq/1brc-in-python-with-dask-3cdee6a56a2d).\r\n\r\n**Steps/Code to reproduce bug**\r\n```python\r\nimport cudf\r\nimport cupy as cp\r\n\r\n# Generate some sample data similar to the data in 1BRC\r\nstations = cudf.Series(['Ankara', 'Kampala', 'Tallinn', 'Gjoa Haven', 'Luanda', 'Cairo', 'Phnom Penh', 'Thessaloniki', 'Split', 'Palermo', 'Ouarzazate', 'Mandalay'])\r\ndf = cudf.DataFrame({        \r\n        \"station\": cp.random.randint(0, len(stations)-1, 10_000_000),\r\n        \"measure\": cp.random.normal(0, 10.0, 10_000_000)\r\n    })\r\ndf.station = df.station.map(stations)\r\n\r\n# Perform the grouby aggregation\r\ndf = df.groupby(\"station\").agg([\"min\", \"max\", \"mean\"])\r\ndf.columns = df.columns.droplevel()\r\n\r\n# Sort\r\ndf.sort_values(\"station\") # <------------ Raises a KeyError\r\n\r\n# It works in Pandas\r\ndf.to_pandas().sort_values(\"station\")  # Works!\r\n```\r\n\r\n```pytb\r\n---------------------------------------------------------------------------\r\nKeyError                                  Traceback (most recent call last)\r\nCell In[10], line 1\r\n----> 1 df.sort_values(\"station\")\r\n\r\nFile /opt/conda/lib/python3.10/site-packages/cudf/core/indexed_frame.py:2459, in IndexedFrame.sort_values(self, by, axis, ascending, inplace, kind, na_position, ignore_index)\r\n   2454     return self\r\n   2456 # argsort the `by` column\r\n   2457 out = self._gather(\r\n   2458     GatherMap.from_column_unchecked(\r\n-> 2459         self._get_columns_by_label(by)._get_sorted_inds(\r\n   2460             ascending=ascending, na_position=na_position\r\n   2461         ),\r\n   2462         len(self),\r\n   2463         nullify=False,\r\n   2464     ),\r\n   2465     keep_index=not ignore_index,\r\n   2466 )\r\n   2467 if (\r\n   2468     isinstance(self, cudf.core.dataframe.DataFrame)\r\n   2469     and self._data.multiindex\r\n   2470 ):\r\n   2471     out.columns = self._data.to_pandas_index()\r\n\r\nFile /opt/conda/lib/python3.10/site-packages/nvtx/nvtx.py:115, in annotate.__call__.<locals>.inner(*args, **kwargs)\r\n    112 @wraps(func)\r\n    113 def inner(*args, **kwargs):\r\n    114     libnvtx_push_range(self.attributes, self.domain.handle)\r\n--> 115     result = func(*args, **kwargs)\r\n    116     libnvtx_pop_range(self.domain.handle)\r\n    117     return result\r\n\r\nFile /opt/conda/lib/python3.10/site-packages/cudf/core/dataframe.py:1959, in DataFrame._get_columns_by_label(self, labels, downcast)\r\n   1950 @_cudf_nvtx_annotate\r\n   1951 def _get_columns_by_label(\r\n   1952     self, labels, *, downcast=False\r\n   1953 ) -> Self | Series:\r\n   1954     \"\"\"\r\n   1955     Return columns of dataframe by `labels`\r\n   1956 \r\n   1957     If downcast is True, try and downcast from a DataFrame to a Series\r\n   1958     \"\"\"\r\n-> 1959     ca = self._data.select_by_label(labels)\r\n   1960     if downcast:\r\n   1961         if is_scalar(labels):\r\n\r\nFile /opt/conda/lib/python3.10/site-packages/cudf/core/column_accessor.py:381, in ColumnAccessor.select_by_label(self, key)\r\n    379     if any(isinstance(k, slice) for k in key):\r\n    380         return self._select_by_label_with_wildcard(key)\r\n--> 381 return self._select_by_label_grouped(key)\r\n\r\nFile /opt/conda/lib/python3.10/site-packages/cudf/core/column_accessor.py:536, in ColumnAccessor._select_by_label_grouped(self, key)\r\n    535 def _select_by_label_grouped(self, key: Any) -> ColumnAccessor:\r\n--> 536     result = self._grouped_data[key]\r\n    537     if isinstance(result, cudf.core.column.ColumnBase):\r\n    538         return self.__class__({key: result}, multiindex=self.multiindex)\r\n\r\nKeyError: 'station'\r\n```\r\n\r\n**Expected behavior**\r\nThe same code works in Pandas/Numpy.\r\n\r\n**Environment overview (please complete the following information)**\r\n\r\n```bash\r\ndocker run --gpus all --pull always --rm -it \\\r\n    --shm-size=1g --ulimit memlock=-1 --ulimit stack=67108864 \\\r\n    -p 8888:8888 -p 8787:8787 -p 8786:8786 \\\r\n    rapidsai/notebooks:23.12-cuda12.0-py3.10\r\n```\r\n\r\n**Additional context**\r\nAdd any other context about the problem here.\r\n",
    "closed_by": null,
    "reactions": {
        "url": "https://api.github.com/repos/rapidsai/cudf/issues/14794/reactions",
        "total_count": 0,
        "+1": 0,
        "-1": 0,
        "laugh": 0,
        "hooray": 0,
        "confused": 0,
        "heart": 0,
        "rocket": 0,
        "eyes": 0
    },
    "timeline_url": "https://api.github.com/repos/rapidsai/cudf/issues/14794/timeline",
    "performed_via_github_app": null,
    "state_reason": null
}