{
    "login": "shrshi",
    "id": 7304582,
    "node_id": "MDQ6VXNlcjczMDQ1ODI=",
    "avatar_url": "https://avatars.githubusercontent.com/u/7304582?v=4",
    "gravatar_id": "",
    "url": "https://api.github.com/users/shrshi",
    "html_url": "https://github.com/shrshi",
    "followers_url": "https://api.github.com/users/shrshi/followers",
    "following_url": "https://api.github.com/users/shrshi/following{/other_user}",
    "gists_url": "https://api.github.com/users/shrshi/gists{/gist_id}",
    "starred_url": "https://api.github.com/users/shrshi/starred{/owner}{/repo}",
    "subscriptions_url": "https://api.github.com/users/shrshi/subscriptions",
    "organizations_url": "https://api.github.com/users/shrshi/orgs",
    "repos_url": "https://api.github.com/users/shrshi/repos",
    "events_url": "https://api.github.com/users/shrshi/events{/privacy}",
    "received_events_url": "https://api.github.com/users/shrshi/received_events",
    "type": "User",
    "site_admin": false,
    "name": "Shruti Shivakumar",
    "company": "NVIDIA",
    "blog": "",
    "location": "Santa Clara, CA",
    "email": "shruti.shivakumar@gmail.com",
    "hireable": null,
    "bio": "HPC @rapidsai.\r\nC++, CUDA, parallel computing. \r\nPhD in Computational Science and Engineering from Georgia Institute of Technology.",
    "twitter_username": null,
    "public_repos": 18,
    "public_gists": 0,
    "followers": 1,
    "following": 1,
    "created_at": "2014-04-15T16:08:46Z",
    "updated_at": "2024-06-04T23:08:19Z"
}